[
  {
    "label": "Nome Oficial",
    "type": "text",
    "id": "Nome_Oficial",
    "htmlFor": "Nome_Oficial",
    "name": "Nome_Oficial"
  },
  {
    "label": "Nome Fantasia",
    "type": "text",
    "id": "Nome_Fantasia",
    "htmlFor": "Nome_Fantasia",
    "name": "Nome_Fantasia"
  },
  {
    "label": "CNPJ/CPF",
    "type": "text",
    "id": "CNPJ_CPF",
    "htmlFor": "CNPJ_CPF",
    "name": "CNPJ_CPF"
  },
  {
    "label": "Tipo de organização",
    "options": [],
    "id": "Tipo_Ator",
    "htmlFor": "Tipo_Ator",
    "name": "Tipo_Ator"
  },
  {
    "label": "Setor Principal de Atuação",
    "options": [],
    "id": "Setor_Principal_Atuacao",
    "htmlFor": "Setor_Principal_Atuacao",
    "name": "Setor_Principal_Atuacao"
  },
  {
    "label": "Setor Secundário de Atuação",
    "options": [
      "Agroalimentar",
      "Recursos Florestais",
      "Recursos Minerais",
      "TI e Automação",
      "Comércio",
      "Serviços",
      "Indústria Geral",
      "Educação",
      "Saúde"
    ],
    "id": "Setores_Secundarios_Atuacao",
    "htmlFor": "Setores_Secundarios_Atuacao",
    "name": "Setores_Secundarios_Atuacao"
  },
  {
    "label": "Descrição das atividades",
    "name": "Descricao_Atividades",
    "rows": "5",
    "id": "Descricao_Atividades",
    "htmlFor": "Descricao_Atividades"
  },
  {
    "label": "Porte",
    "options": [
      "Micro",
      "Pequena",
      "Média",
      "Grande",
      "Startup",
      "Sem Fins Lucrativos"
    ],
    "id": "Porte",
    "htmlFor": "Porte",
    "name": "Porte"
  },
  {
    "label": "CEP",
    "type": "text",
    "id": "Endereco_CEP",
    "htmlFor": "Endereco_CEP",
    "name": "Endereco_CEP"
  },
  {
    "label": "Endereço",
    "type": "text",
    "id": "Endereco_Logradouro",
    "htmlFor": "Endereco_Logradouro",
    "name": "Endereco_Logradouro"
  },
  {
    "label": "Número",
    "type": "text",
    "id": "Endereco_Numero",
    "htmlFor": "Endereco_Numero",
    "name": "Endereco_Numero"
  },
  {
    "label": "Bairro",
    "type": "text",
    "id": "Endereco_Bairro",
    "htmlFor": "Endereco_Bairro",
    "name": "Endereco_Bairro"
  },
  {
    "label": "Cidade",
    "type": "text",
    "id": "Endereco_Cidade",
    "htmlFor": "Endereco_Cidade",
    "name": "Endereco_Cidade"
  },
  {
    "label": "UF",
    "options": [
      "AC",
      "AL",
      "AP",
      "AM",
      "BA",
      "CE",
      "DF",
      "ES",
      "GO",
      "MA",
      "MT",
      "MS",
      "MG",
      "PA",
      "PB",
      "PR",
      "PE",
      "PI",
      "RJ",
      "RN",
      "RS",
      "RO",
      "RR",
      "SC",
      "SP",
      "SE",
      "TO"
    ],
    "id": "Endereco_UF",
    "htmlFor": "Endereco_UF",
    "name": "Endereco_UF"
  },
  {
    "label": "Complemento",
    "type": "text",
    "id": "Endereco_Complemento",
    "htmlFor": "Endereco_Complemento",
    "name": "Endereco_Complemento"
  },
  {
    "label": "Telefone Principal",
    "type": "text",
    "id": "Telefone_Principal",
    "htmlFor": "Telefone_Principal",
    "name": "Telefone_Principal"
  },
  {
    "label": "Email Principal",
    "type": "email",
    "id": "Email_Principal",
    "htmlFor": "Email_Principal",
    "name": "Email_Principal"
  },
  {
    "label": "Ano Fundação",
    "type": "text",
    "id": "Ano_Fundacao",
    "htmlFor": "Ano_Fundacao",
    "name": "Ano_Fundacao"
  },
  {
    "label": "Website",
    "type": "text",
    "id": "Website",
    "htmlFor": "Website",
    "name": "Website"
  },
  {
    "label": "Redes Sociais",
    "type": "text",
    "id": "Redes_Sociais",
    "htmlFor": "Redes_Sociais",
    "name": "Redes_Sociais"
  },
  {
    "label": "Telefone Contato Principal",
    "type": "text",
    "id": "Telefone_Contato_Principal",
    "htmlFor": "Telefone_Contato_Principal",
    "name": "Telefone_Contato_Principal"
  },
  {
    "label": "Nome Contato Principal",
    "type": "text",
    "id": "Nome_Contato_Principal",
    "htmlFor": "Nome_Contato_Principal",
    "name": "Nome_Contato_Principal"
  },
  {
    "label": "Cargo Contato Principal",
    "type": "text",
    "id": "Cargo_Contato_Principal",
    "htmlFor": "Cargo_Contato_Principal",
    "name": "Cargo_Contato_Principal"
  },
  {
    "label": "E-mail Contato Principal",
    "type": "email",
    "id": "Email_Contato_Principal",
    "htmlFor": "Email_Contato_Principal",
    "name": "Email_Contato_Principal"
  },
  {
    "label": "Status da Empresa",
    "options": ["Ativo", "Inativo", "Prospect"],
    "id": "Status_Ator",
    "htmlFor": "Status_Ator",
    "name": "Status_Ator"
  },
  {
    "label": "Origem do cadastro",
    "type": "text",
    "id": "Origem_Cadastro",
    "htmlFor": "Origem_Cadastro",
    "name": "Origem_Cadastro"
  },
  {
    "label": "Observações Gerais",
    "name": "Observacoes_Gerais",
    "rows": "5",
    "id": "Observacoes_Gerais",
    "htmlFor": "Observacoes_Gerais"
  }
]
